zodic/__init__.py
zodic/core/__init__.py
zodic/core/base.py
zodic/core/errors.py
zodic/core/types.py
zodic/schemas/__init__.py
zodic/schemas/collections.py
zodic/schemas/enums.py
zodic/schemas/primitives.py
zodic/schemas/special.py
zodic-0.2.0.dist-info/LICENSE
zodic-0.2.0.dist-info/METADATA
zodic-0.2.0.dist-info/WHEEL
zodic-0.2.0.dist-info/RECORD
