Metadata-Version: 2.3
Name: zodic
Version: 0.2.0
Summary: A TypeScript Zod-inspired validation library for Python with excellent type safety and developer experience
License: MIT
Keywords: validation,schema,type-checking,parsing,data-validation,zod,typescript,type-safety
Author: Touhidul Alam Seyam
Author-email: seyamalam41@gmail.com
Requires-Python: >=3.9,<4.0
Classifier: Development Status :: 4 - Beta
Classifier: Intended Audience :: Developers
Classifier: License :: OSI Approved :: MIT License
Classifier: Operating System :: OS Independent
Classifier: Programming Language :: Python :: 3
Classifier: Programming Language :: Python :: 3.9
Classifier: Programming Language :: Python :: 3.10
Classifier: Programming Language :: Python :: 3.11
Classifier: Programming Language :: Python :: 3.12
Classifier: Programming Language :: Python :: 3.13
Classifier: Topic :: Software Development :: Libraries :: Python Modules
Classifier: Topic :: Software Development :: Quality Assurance
Classifier: Topic :: Utilities
Classifier: Typing :: Typed
Requires-Dist: typing-extensions (>=4.0.0,<5.0.0) ; python_version < "3.11"
Project-URL: Documentation, https://github.com/Seyamalam/zodic
Project-URL: Homepage, https://github.com/Seyamalam/zodic
Project-URL: Repository, https://github.com/Seyamalam/zodic
